twisted_strings/__init__.py
twisted_strings/_structs/__init__.py
twisted_strings/_structs/_data.py
twisted_strings/_structs/_model.py
twisted_strings/dynamics/__init__.py
twisted_strings/dynamics/_components.py
twisted_strings/dynamics/_energy.py
twisted_strings/dynamics/_problems.py
twisted_strings/kinematics/__init__.py
twisted_strings/kinematics/_acceleration.py
twisted_strings/kinematics/_constraints.py
twisted_strings/kinematics/_position.py
twisted_strings/kinematics/_velocity.py
twisted_strings-0.0.2.dist-info/METADATA
twisted_strings-0.0.2.dist-info/WHEEL
twisted_strings-0.0.2.dist-info/top_level.txt
twisted_strings-0.0.2.dist-info/RECORD
