Metadata-Version: 2.1
Name: twisted-strings
Version: 0.0.2
Summary: twisted string actuators
Author-email: Simeon Nedelchev <simkaned@gmail.com>, Lev Kozlov <l.kozlov@kaist.ac.kr>
Project-URL: homepage, https://github.com/based-robotics/tsa
Project-URL: repository, https://github.com/based-robotics/tsa.git
Requires-Python: >=3.10
Requires-Dist: numpy
Provides-Extra: dev
Requires-Dist: pre-commit; extra == "dev"
Requires-Dist: pytest; extra == "dev"
